bm_group.py
bm_group-0.1.1.dist-info/licenses/LICENSE
bm_group-0.1.1.dist-info/METADATA
bm_group-0.1.1.dist-info/WHEEL
bm_group-0.1.1.dist-info/entry_points.txt
bm_group-0.1.1.dist-info/top_level.txt
bm_group-0.1.1.dist-info/RECORD
