Metadata-Version: 2.4
Name: bm-group
Version: 0.1.1
Summary: CLI tool to group SMILES by Bemis–Murcko scaffold, with deterministic 3D conformer generation and on-disk caching (RDKit-based).
License: MIT License
Requires-Python: >=3.10
License-File: LICENSE
Requires-Dist: tqdm>=4.0
Requires-Dist: rdkit>=2024.03.5
Dynamic: license-file
